omnikeeper_client/__init__.py
omnikeeper_client/apiclient.py
omnikeeper_client/ci.py
omnikeeper_client/dataframes.py
omnikeeper_client/issues.py
omnikeeper_client/layer.py
omnikeeper_client/pyd.py
omnikeeper_client/simple_traits.py
omnikeeper_client/trait.py
omnikeeper_client/traitentities.py
omnikeeper_client/typing.py
omnikeeper_client/util.py
omnikeeper_client-6.0.2.dist-info/LICENSE
omnikeeper_client-6.0.2.dist-info/METADATA
omnikeeper_client-6.0.2.dist-info/WHEEL
omnikeeper_client-6.0.2.dist-info/top_level.txt
omnikeeper_client-6.0.2.dist-info/RECORD
