Metadata-Version: 2.1
Name: omnikeeper-client
Version: 6.0.2
Summary: Python library containing helper functions for implementing omnikeeper clients
Author: Maximilian Csuk
License: Apache 2.0
License-File: LICENSE
Requires-Dist: appengine-python-standard ~=1.1
Requires-Dist: gql ~=3.4
Requires-Dist: oauthlib ~=3.2
Requires-Dist: pandas >=2.0
Requires-Dist: python-json-logger ~=2.0
Requires-Dist: requests-oauthlib ~=1.3
Requires-Dist: requests-toolbelt ~=0.10
Requires-Dist: webcolors ~=1.3
Requires-Dist: pydantic ~=2.6
